govee_btled_H613B/__init__.py
govee_btled_H613B/const.py
govee_btled_H613B/exceptions.py
govee_btled_H613B/govee_btled_H613B.py
govee_btled_H613B/models.py
govee_btled_H613B/utils.py
govee_btled_h613b-0.0.6.dist-info/LICENSE
govee_btled_h613b-0.0.6.dist-info/METADATA
govee_btled_h613b-0.0.6.dist-info/WHEEL
govee_btled_h613b-0.0.6.dist-info/RECORD
